{
    "status": "ok",
    "totalResults": 37,
    "articles": [
        {
            "source": {
                "id": null,
                "name": "CNBC"
            },
            "author": "Ruxandra Iordache, Natasha Turak",
            "title": "Israel-Hamas war live updates: Putin and Assad urge end to violence in Gaza; Biden stresses need for 'path to Palestinian state' - CNBC",
            "description": "Israel is on its 10th day of an aerial bombardment campaign of the Gaza Strip as it readies for a potential ground invasion.",
            "url": "https://www.cnbc.com/2023/10/16/israel-hamas-war-updates-latest-news-on-gaza.html",
            "urlToImage": "https://image.cnbcfm.com/api/v1/image/107317726-1697459261210-gettyimages-1726469052-AFP_33Y98BJ.jpeg?v=1697459365&w=1920&h=1080",
            "publishedAt": "2023-10-16T12:20:00Z",
            "content": "The office of Israeli Prime Minister Benjamin Netanyahu appeared to deny the existence of a humanitarian corridor allowing the passage of foreign nationals out of the Gaza Strip.\r\n\"There is currently… [+1497 chars]"
        },
        {
            "source": {
                "id": "cnn",
                "name": "CNN"
            },
            "author": "Chris Boyette, Keith Allen",
            "title": "Palestinian-American boy killed and his mother injured after landlord stabs them because they were Muslim, authorities say - CNN",
            "description": "A Chicago-area landlord was arrested and charged with murder and hate crimes after authorities said he stabbed and killed a 6-year-old boy and seriously wounded his mother, allegedly because the tenants are Muslim.",
            "url": "https://www.cnn.com/2023/10/15/us/chicago-landlord-attack-muslim-boy-mother/index.html",
            "urlToImage": "https://media.cnn.com/api/v1/images/stellar/prod/231015172306-wadea-al-fayoume.jpg?c=16x9&q=w_800,c_fill",
            "publishedAt": "2023-10-16T12:02:00Z",
            "content": "A Chicago-area landlord was arrested and charged with murder and hate crimes after authorities said he stabbed and killed a 6-year-old boy and seriously wounded his mother, allegedly because the tena… [+6365 chars]"
        },
        {
            "source": {
                "id": "reuters",
                "name": "Reuters"
            },
            "author": "Abinaya V",
            "title": "Drug retailer Rite Aid files for bankruptcy amid rising debt, opioid litigation - Reuters",
            "description": "Debt-laden Rite Aid <a href=\"https://www.reuters.com/markets/companies/RAD.N\" target=\"_blank\">(RAD.N)</a> filed for bankruptcy protection on Sunday and said it would close underperforming stores, as the drugstore chain comes under pressure from lawsuits alleg…",
            "url": "https://www.reuters.com/markets/deals/drug-retailer-rite-aid-files-bankruptcy-protection-2023-10-16/",
            "urlToImage": "https://www.reuters.com/resizer/suwBu1BBaHMX3Lrfobos7ip-YTE=/1200x628/smart/filters:quality(80)/cloudfront-us-east-2.images.arcpublishing.com/reuters/OCR436K2G5IDNAVLK47U3V7CZI.jpg",
            "publishedAt": "2023-10-16T11:57:00Z",
            "content": "Oct 16 (Reuters) - Debt-laden Rite Aid (RAD.N) filed for bankruptcy protection on Sunday and said it would close underperforming stores, as the drugstore chain comes under pressure from lawsuits alle… [+1660 chars]"
        },
        {
            "source": {
                "id": null,
                "name": "Cosmopolitan.com"
            },
            "author": "Mehera  Bonner",
            "title": "Taylor Swift Rocks Sheer Green Top With Bustier for PDA-Filled Date Night With Travis Kelce - Cosmopolitan",
            "description": "Psst: Taylor's top is Jean Paul Gaultier, and it's still avail!",
            "url": "https://www.cosmopolitan.com/entertainment/celebs/a45545220/taylor-swift-sheer-green-top-travis-kelce-date/",
            "urlToImage": "https://hips.hearstapps.com/hmg-prod/images/taylor-swift-and-travis-kelce-have-dinner-at-waverly-inn-on-news-photo-1697453396.jpg?crop=1.00xw:0.565xh;0,0.0881xh&resize=1200:*",
            "publishedAt": "2023-10-16T11:12:19Z",
            "content": "Taylor Swift and Travis Kelce went ~SNL Official~ over the weekend, and just stepped out for the second night in a row. The couple were spotted holding hands while leaving the Waverly Inn in New York… [+2238 chars]"
        },
        {
            "source": {
                "id": "cnn",
                "name": "CNN"
            },
            "author": "Laura He",
            "title": "Oil prices fluctuate as concerns mount over Middle East tensions - CNN",
            "description": "Oil prices rose above $91 a barrel Monday as diplomatic efforts to address the crisis in the Middle East intensified, but slipped back later in the day, standing near their Friday level.",
            "url": "https://www.cnn.com/2023/10/16/investing/global-markets-oil-intl-hnk/index.html",
            "urlToImage": "https://media.cnn.com/api/v1/images/stellar/prod/231016000100-08-israel-gaza-101523.jpg?c=16x9&q=w_800,c_fill",
            "publishedAt": "2023-10-16T10:37:00Z",
            "content": "Oil prices rose above $91 a barrel Monday as diplomatic efforts to address the crisis in the Middle East intensified, but slipped back later in the day, standing near their Friday level. \r\nInvestors … [+2419 chars]"
        },
        {
            "source": {
                "id": null,
                "name": "CBS Sports"
            },
            "author": "",
            "title": "Astros vs. Rangers: Explaining unusual double play as Jose Altuve makes baserunning mistake in ALCS Game 1 - CBS Sports",
            "description": "A ball off Alex Bregman's bat looked like it might tie the game... instead it resulted in two outs",
            "url": "https://www.cbssports.com/mlb/news/astros-vs-rangers-explaining-unusual-double-play-as-jose-altuve-makes-baserunning-mistake-in-alcs-game-1/",
            "urlToImage": "https://sportshub.cbsistatic.com/i/r/2023/10/16/a9d7bc72-b95d-4a19-ba82-ba38861276b8/thumbnail/1200x675/f148e2e594a8159f54b9016056d84b06/jose-altuve-getty-1.png",
            "publishedAt": "2023-10-16T10:20:00Z",
            "content": "The Texas Rangers defeated the Houston Astros2-0 on Sunday night in Game 1 of the American League Championship Series. The Rangers' win did not come without some late-inning controversy, however. The… [+1953 chars]"
        },
        {
            "source": {
                "id": null,
                "name": "Hollywood Reporter"
            },
            "author": "Scott Roxborough",
            "title": "Warner Bros. Discovery’s Max Details 2024 European Rollout Plans - Hollywood Reporter",
            "description": "The conglomerate will bow the streamer in 22 European territories next year, top executives told MIPCOM in Cannes.",
            "url": "https://www.hollywoodreporter.com/tv/tv-news/hbo-max-europe-2024-rollout-mipcom-1235619251/",
            "urlToImage": "https://www.hollywoodreporter.com/wp-content/uploads/2020/10/Zeiler-1601546024.jpg?w=1024",
            "publishedAt": "2023-10-16T10:15:13Z",
            "content": "Warner Bros. Discovery will launch its Max streaming service across 22 European countries starting in the spring. \r\nGerhard Zeiler, president of international at Warner Bros. Discovery, and Leah Hopp… [+1688 chars]"
        },
        {
            "source": {
                "id": "axios",
                "name": "Axios"
            },
            "author": "Axios",
            "title": "Biden says Israeli occupation of Gaza would be a \"big mistake\" - Axios",
            "description": null,
            "url": "https://www.axios.com/2023/10/15/biden-60-minutes-israel-hamas-war",
            "urlToImage": null,
            "publishedAt": "2023-10-16T10:12:35Z",
            "content": null
        },
        {
            "source": {
                "id": null,
                "name": "[Removed]"
            },
            "author": null,
            "title": "[Removed]",
            "description": "[Removed]",
            "url": "https://removed.com",
            "urlToImage": null,
            "publishedAt": "1970-01-01T00:00:00Z",
            "content": "[Removed]"
        },
        {
            "source": {
                "id": null,
                "name": "INSIDER"
            },
            "author": "Ayomikun Adekaiyero",
            "title": "Will Smith's reaction to Jada Pinkett Smith memoir revelations - Insider",
            "description": "Jada Pinkett Smith said she and Will Smith had been separated since 2016. Smith appears to have posted a humorous Instagram video in response.",
            "url": "https://www.insider.com/will-smith-reaction-jada-pinkett-smith-memoir-book-separation-2023-10",
            "urlToImage": "https://i.insider.com/652cf35555f52b01b35ffecb?width=1200&format=jpeg",
            "publishedAt": "2023-10-16T09:38:00Z",
            "content": "Will Smith has seemingly reacted to the ongoing online discourse about his marriage to Jada Pinkett Smith, who said last week they had been separated since 2016.\r\nOn Sunday, Smith posted a video of h… [+2233 chars]"
        },
        {
            "source": {
                "id": "reuters",
                "name": "Reuters"
            },
            "author": "Philip Pullella",
            "title": "Jerusalem Catholic Patriarch offers to be exchanged for Gaza hostages - Reuters",
            "description": "Pope Francis' representative in the Holy Land said on Monday he was willing to exchange himself for Israeli children taken hostage by Hamas and held in Gaza.",
            "url": "https://www.reuters.com/world/middle-east/jerusalem-catholic-patriarch-offers-be-exchanged-gaza-hostages-2023-10-16/",
            "urlToImage": "https://www.reuters.com/resizer/RTjGq-OjaKAFp8NwVc5GwR9bzQs=/1200x628/smart/filters:quality(80)/cloudfront-us-east-2.images.arcpublishing.com/reuters/CJXH2DUP5JJWTIHZQ3RWR5CCPU.jpg",
            "publishedAt": "2023-10-16T09:10:00Z",
            "content": "VATICAN CITY, Oct 16 (Reuters) - Pope Francis' representative in the Holy Land said on Monday he was willing to exchange himself for Israeli children taken hostage by Hamas and held in Gaza.\r\nCardina… [+1898 chars]"
        },
        {
            "source": {
                "id": null,
                "name": "Yahoo Entertainment"
            },
            "author": "CHRIS MEGERIAN",
            "title": "Biden postpones trip to Colorado to discuss domestic agenda as the Israel-Hamas conflict intensifies - Yahoo Finance",
            "description": "President Joe Biden postponed a trip to Colorado on Monday to stay in Washington and focus on the growing conflict in the Middle East, setting aside an...",
            "url": "https://finance.yahoo.com/news/biden-picks-boebert-foil-economic-090514815.html",
            "urlToImage": "https://s.yimg.com/ny/api/res/1.2/8mDUkI3Fa5i28nJnrWuR6A--/YXBwaWQ9aGlnaGxhbmRlcjt3PTEyMDA7aD04MDA-/https://media.zenfs.com/en/ap_finance_articles_694/cbaa46cb911380f2c90c219a837f2506",
            "publishedAt": "2023-10-16T09:05:14Z",
            "content": "WASHINGTON (AP) President Joe Biden postponed a trip to Colorado on Monday to stay in Washington and focus on the growing conflict in the Middle East, setting aside an opportunity to pitch his econom… [+3986 chars]"
        },
        {
            "source": {
                "id": null,
                "name": "NPR"
            },
            "author": "",
            "title": "Scientists build the largest-ever atlas of over 3,000 cells in the human brain : Shots - Health News - NPR",
            "description": "A new atlas of the human brain could help explain abilities like language – and vulnerabilities, like Alzheimer's disease.",
            "url": "https://www.npr.org/sections/health-shots/2023/10/16/1205780690/largest-ever-map-human-brain-atlas-3000-cells-alzheimers-schizophrenia",
            "urlToImage": "https://media.npr.org/assets/img/2023/10/13/gettyimages-1252707284_wide-e89cae545ca5e29583c4b92a0277d2b64839fa7b-s1400-c100.jpg",
            "publishedAt": "2023-10-16T09:01:00Z",
            "content": "Scientists have built an enormous atlas of the human brain that could help them chart a path toward preventing and treating many different neurological disorders.\r\nAndriy Onufriyenko/Getty Images\r\nSc… [+5106 chars]"
        },
        {
            "source": {
                "id": null,
                "name": "NPR"
            },
            "author": "",
            "title": "Judge will consider partial gag order on Donald Trump after inflammatory posts - NPR",
            "description": "Prosecutors argue that the former president's inflammatory remarks undermine confidence in the courts and could bias potential jurors.",
            "url": "https://www.npr.org/2023/10/16/1205769475/trump-gag-order",
            "urlToImage": "https://media.npr.org/assets/img/2023/10/13/gettyimages-1719485959_wide-85912930108d04364b0a24e536e66524398c03ca-s1400-c100.jpg",
            "publishedAt": "2023-10-16T09:00:30Z",
            "content": "Prosecutors are seeking a partial gag order against former President Donald Trump.\r\nAlon Skuy/Getty Images\r\nThe U.S. Justice Department said former President Donald Trump undermined the 2020 election… [+3821 chars]"
        },
        {
            "source": {
                "id": "nbc-news",
                "name": "NBC News"
            },
            "author": "Berkeley Lovelace Jr.",
            "title": "Does insurance cover weight loss drugs? Here's what it would take. - NBC News",
            "description": "Why aren't weight loss drugs covered by insurance? Here's what it would take to get health insurance to pay for Wegovy, Ozempic and semaglutide.",
            "url": "https://www.nbcnews.com/health/health-news/insurance-cover-weight-loss-drugs-take-rcna120091",
            "urlToImage": "https://media-cldnry.s-nbcnews.com/image/upload/t_nbcnews-fp-1200-630,f_auto,q_auto:best/rockcms/2023-10/231013-wegovy-insurance-weight-loss-kh-2db8d0.jpg",
            "publishedAt": "2023-10-16T09:00:00Z",
            "content": "The makers of Ozempic, Wegovy and Mounjaro are racing to prove that the incredibly popular drugs have health benefits beyond weight lossand diabetes.Doing so, they say, will make it easier for patien… [+7257 chars]"
        },
        {
            "source": {
                "id": null,
                "name": "SciTechDaily"
            },
            "author": null,
            "title": "Dark Matter and Galactic Collisions: Harvard Astronomers Explain the Milky Way's Mysterious Warp - SciTechDaily",
            "description": "Astronomers’ results bolster the hypothesis of how our galaxy evolved. The Milky Way is often depicted as a flat, spinning disk of dust, gas, and stars. But if you could zoom out and take an edge-on photo, it actually has a distinctive warp — as if you tried …",
            "url": "https://scitechdaily.com/dark-matter-and-galactic-collisions-harvard-astronomers-explain-the-milky-ways-mysterious-warp/",
            "urlToImage": "https://scitechdaily.com/images/Edge-On-Galaxy-ESO-510-G13.jpg",
            "publishedAt": "2023-10-16T08:29:43Z",
            "content": "ByHarvard UniversityOctober 16, 2023\r\nHarvard astronomers suggest the Milky Ways warped shape is due to an irregular dark matter halo. This supports theories of a past galactic collision and offers i… [+5211 chars]"
        },
        {
            "source": {
                "id": "financial-times",
                "name": "Financial Times"
            },
            "author": "Barbara Erling, Raphael Minder",
            "title": "Polish exit polls give ex-PM Donald Tusk potential route back to power - Financial Times",
            "description": "Ruling Law and Justice party expected to come first but without enough votes to govern alone or with the far right",
            "url": "https://www.ft.com/content/a4447b80-da74-408b-8cdd-7bbec90613e6",
            "urlToImage": "https://www.ft.com/__origami/service/image/v2/images/raw/https%3A%2F%2Fwww.ft.com%2F__origami%2Fservice%2Fimage%2Fv2%2Fimages%2Fraw%2Fhttps%253A%252F%252Fd1e00ek4ebabms.cloudfront.net%252Fproduction%252F1f040547-5c25-429f-94f7-30d555cd9cbd.jpg%3Fsource%3Dnext-article%26fit%3Dscale-down%26quality%3Dhighest%26width%3D700%26dpr%3D1?source=next-opengraph&fit=scale-down&width=900",
            "publishedAt": "2023-10-16T07:15:02Z",
            "content": "Donald Tusk has secured a potential path to power in Poland, according to two election exit polls that give the former European Council president the upper hand over his rightwing rivals, the ruling … [+5159 chars]"
        },
        {
            "source": {
                "id": "reuters",
                "name": "Reuters"
            },
            "author": "Reuters",
            "title": "Egyptian sources say ceasefire agreed to allow Rafah re-opening, Netanyahu denies - Reuters",
            "description": "Egypt, Israel and the U.S. agreed to a ceasefire in southern Gaza beginning at 0600 GMT coinciding with the re-opening of the Rafah border crossing, two Egyptian security sources said on Monday, to allow in aid and evacuations of foreigners.",
            "url": "https://www.reuters.com/world/egypt-us-israel-agree-ceasefire-southern-gaza-opening-rafah-crossing-0600-gmt-2023-10-16/",
            "urlToImage": "https://www.reuters.com/resizer/4FXqR9Oao3kyDhRZOKDkylrk388=/1186x621/smart/filters:quality(80)/cloudfront-us-east-2.images.arcpublishing.com/reuters/BQL3H3N33JI5TLX5I7VCZKLEIM.jpg",
            "publishedAt": "2023-10-16T07:07:00Z",
            "content": "CAIRO, Oct 16 (Reuters) - Egypt, Israel and the U.S. agreed to a ceasefire in southern Gaza beginning at 0600 GMT coinciding with the re-opening of the Rafah border crossing, two Egyptian security so… [+3144 chars]"
        },
        {
            "source": {
                "id": null,
                "name": "Push Square"
            },
            "author": "Push Square",
            "title": "Hot Wheels Unleashed 2: Turbocharged Review (PS5) - Push Square",
            "description": "Magnificent modifications",
            "url": "https://www.pushsquare.com/reviews/ps5/hot-wheels-unleashed-2-turbocharged",
            "urlToImage": "https://images.pushsquare.com/514569d7e2178/1280x720.jpg",
            "publishedAt": "2023-10-16T07:00:00Z",
            "content": "We remember as kids setting up our Hot Wheels Octoblast and Shark Park race tracks every weekend, launching cars round them at high speeds while avoiding the giant creatures. It always brought such j… [+5174 chars]"
        },
        {
            "source": {
                "id": null,
                "name": "New York Post"
            },
            "author": "Ryan Dunleavy",
            "title": "Heroes, zeros from Jets' win vs. Eagles: Tony Adams interception set up winning TD - New York Post ",
            "description": "Hero, zero and full blitz from the Jets’ 20-14 victory against the Eagles on Sunday.",
            "url": "https://nypost.com/2023/10/16/heros-zeros-from-jets-win-vs-eagles-tony-adams-interception-set-up-winning-td/",
            "urlToImage": "https://nypost.com/wp-content/uploads/sites/2/2023/10/newspress-collage-qbv7ytrtn-1697435158817.jpg?quality=75&strip=all&1697420787&w=1024",
            "publishedAt": "2023-10-16T06:02:00Z",
            "content": "Hero, zero and full blitz from the Jets’ 20-14 victory against the Eagles on Sunday.\r\nHero\r\nJust after the two-minute warning, safety Tony Adams intercepted a third-and-9 pass and ran it back 45 yard… [+1088 chars]"
        }
    ]
}